lxcb/bootstrap.py
lxcb/create.py
lxcb/info.py
lxcb/main.py
lxcb/mount.py
lxc_butler-0.0.5.dist-info/LICENSE
lxc_butler-0.0.5.dist-info/METADATA
lxc_butler-0.0.5.dist-info/WHEEL
lxc_butler-0.0.5.dist-info/entry_points.txt
lxc_butler-0.0.5.dist-info/top_level.txt
lxc_butler-0.0.5.dist-info/RECORD
