Metadata-Version: 2.1
Name: lxc-butler
Version: 0.0.5
Summary: A helper to make working with LXC containers easy and convenient
Home-page: https://github.com/kobus-v-schoor/lxc-butler
Author: Kobus van Schoor
Author-email: v.schoor.kobus@gmail.com
License: MIT License
Platform: UNKNOWN
Classifier: Programming Language :: Python :: 3
Classifier: Topic :: Utilities
Classifier: Operating System :: POSIX :: Linux
Classifier: License :: OSI Approved :: MIT License
Requires-Python: >=3.6
